LICENSE
pyfgaws/__init__.py
pyfgaws/__main__.py
pyfgaws/batch/__init__.py
pyfgaws/batch/api.py
pyfgaws/batch/tests/__init__.py
pyfgaws/batch/tests/test_api.py
pyfgaws/batch/tools.py
pyfgaws/core/__init__.py
pyfgaws/core/logging.py
pyfgaws/core/tests/__init__.py
pyfgaws/core/tests/test_core.py
pyfgaws/logs/__init__.py
pyfgaws/logs/api.py
pyfgaws/logs/tests/__init__.py
pyfgaws/logs/tests/test_api.py
pyfgaws/logs/tools.py
pyfgaws/tests/__init__.py
pyfgaws/tests/test_main.py
pyfgaws-0.2.3.dist-info/entry_points.txt
pyfgaws-0.2.3.dist-info/LICENSE
pyfgaws-0.2.3.dist-info/WHEEL
pyfgaws-0.2.3.dist-info/METADATA
pyfgaws-0.2.3.dist-info/RECORD
